{
"meta": {
    "disclaimer": "https://github.com/hesa/license-db/tree/main/var/disclamer.md",
    "comment": ""
  },
  "name": "GNU Affero General Public License 3.0",
  "scancode_key": "agpl-3.0",
  "spdxid": "AGPL-3.0-only",
  "aliases": [
   "AGPL-3.0",
   "AGPL3.0",
   "AGPL3",
   "AGPL (v3)",
   "Affero General Public License 3.0",
   "GNU Affero General Public License (AGPL-3.0) (v. 3.0)",
   "GNU Affero General Public License v3.0 only",
   "agpl-3.0",
   "GNU AGPLv3",
   "GNU Affero General Public License v3",
   "agpl-v3",
   "GNU AFFERO GENERAL PUBLIC LICENSE, Version 3 (AGPL-3.0)",
   "License :: OSI Approved :: GNU Affero General Public License v3",
   "scancode://agpl-3.0",
   "AGPL 3.0",
   "GNU AFFERO GENERAL PUBLIC LICENSE (AGPL-3)",
   "AGPLv3",
   "GNU AFFERO GENERAL PUBLIC LICENSE Version 3",
   "GNU AFFERO GENERAL PUBLIC LICENSE v3",
   "GNU AFFERO GENERAL PUBLIC LICENSE, version 3",
   "GNU AFFERO PUBLIC LICENSE, Version 3",
   "GNU Affero General Public License (AGPL) v3",
   "GNU Affero General Public License (AGPL) version 3.0",
   "GNU Affero General Public License Version 3",
   "GNU Affero General Public License, version 3",
   "GNU Afferp General Public License (AGPL), Version 3.0",
   "Affero GPLv3",
   "GNO Affero GPL v3.0",
   "AGPL v3",
   "AGPL-V3",
   "AGPL-v3",
   "Affero GPL3",
   "General Affero Public License version 3",
   "Affero GNU Public License Version 3",
   "AGPL-3",
   "scancode:agpl-3.0",
   "osi:AGPL-3.0",
   "AGPLv3.0"
  ]
}
