{
    "NASA-1.3": {
        "NoCopyleft": [
            "BlueOak License List"
        ],
        "WeakCopyleft": [
            "HansHammel license-compatibility-checker"
        ]
    },
    "ClArtistic": {
        "NoCopyleft": [
            "BlueOak License List"
        ],
        "WeakCopyleft": [
            "HansHammel license-compatibility-checker"
        ]
    },
    "APSL-2.0": {
        "WeakCopyleft": [
            "HansHammel license-compatibility-checker"
        ],
        "SaaSCopyleft": [
            "BlueOak License List"
        ]
    },
    "MS-PL": {
        "NoCopyleft": [
            "BlueOak License List",
            "Google OSS Policy"
        ],
        "WeakCopyleft": [
            "HansHammel license-compatibility-checker"
        ]
    },
    "EPL-2.0": {
        "StrongCopyleft": [
            "HansHammel license-compatibility-checker"
        ],
        "WeakCopyleft": [
            "BlueOak License List"
        ]
    },
    "OSL-2.1": {
        "StrongCopyleft": [
            "HansHammel license-compatibility-checker"
        ],
        "SaaSCopyleft": [
            "BlueOak License List",
            "librariesio license-compatibility"
        ]
    },
    "OSL-3.0": {
        "StrongCopyleft": [
            "HansHammel license-compatibility-checker"
        ],
        "SaaSCopyleft": [
            "BlueOak License List",
            "librariesio license-compatibility"
        ]
    },
    "EUPL-1.0": {
        "StrongCopyleft": [
            "HansHammel license-compatibility-checker"
        ],
        "SaaSCopyleft": [
            "BlueOak License List"
        ]
    },
    "OSL-2.0": {
        "StrongCopyleft": [
            "HansHammel license-compatibility-checker"
        ],
        "SaaSCopyleft": [
            "BlueOak License List",
            "librariesio license-compatibility"
        ]
    },
    "Artistic-1.0": {
        "NoCopyleft": [
            "BlueOak License List",
            "Google OSS Policy"
        ],
        "WeakCopyleft": [
            "HansHammel license-compatibility-checker"
        ]
    },
    "RPL-1.5": {
        "StrongCopyleft": [
            "HansHammel license-compatibility-checker"
        ],
        "MaximalCopyleft": [
            "BlueOak License List"
        ],
        "SaaSCopyleft": [
            "librariesio license-compatibility"
        ]
    },
    "CPAL-1.0": {
        "WeakCopyleft": [
            "HansHammel license-compatibility-checker"
        ],
        "SaaSCopyleft": [
            "BlueOak License List"
        ]
    },
    "APSL-1.0": {
        "NoCopyleft": [
            "HansHammel license-compatibility-checker"
        ],
        "SaaSCopyleft": [
            "BlueOak License List"
        ]
    },
    "EUPL-1.1": {
        "StrongCopyleft": [
            "HansHammel license-compatibility-checker"
        ],
        "SaaSCopyleft": [
            "BlueOak License List"
        ]
    },
    "Artistic-1.0-Perl": {
        "NoCopyleft": [
            "BlueOak License List"
        ],
        "WeakCopyleft": [
            "HansHammel license-compatibility-checker"
        ]
    },
    "LPPL-1.3c": {
        "NoCopyleft": [
            "BlueOak License List"
        ],
        "WeakCopyleft": [
            "HansHammel license-compatibility-checker"
        ]
    },
    "OSL-1.0": {
        "StrongCopyleft": [
            "HansHammel license-compatibility-checker"
        ],
        "SaaSCopyleft": [
            "BlueOak License List",
            "librariesio license-compatibility"
        ]
    },
    "RPL-1.1": {
        "StrongCopyleft": [
            "HansHammel license-compatibility-checker"
        ],
        "MaximalCopyleft": [
            "BlueOak License List"
        ],
        "SaaSCopyleft": [
            "librariesio license-compatibility"
        ]
    },
    "CPL-1.0": {
        "StrongCopyleft": [
            "HansHammel license-compatibility-checker"
        ],
        "WeakCopyleft": [
            "BlueOak License List"
        ]
    },
    "APSL-1.1": {
        "WeakCopyleft": [
            "HansHammel license-compatibility-checker"
        ],
        "SaaSCopyleft": [
            "BlueOak License List"
        ]
    },
    "MS-RL": {
        "StrongCopyleft": [
            "HansHammel license-compatibility-checker",
            "librariesio license-compatibility"
        ],
        "WeakCopyleft": [
            "BlueOak License List"
        ]
    },
    "Sleepycat": {
        "StrongCopyleft": [
            "BlueOak License List"
        ],
        "WeakCopyleft": [
            "HansHammel license-compatibility-checker"
        ]
    },
    "Artistic-1.0-cl8": {
        "NoCopyleft": [
            "BlueOak License List"
        ],
        "WeakCopyleft": [
            "HansHammel license-compatibility-checker"
        ]
    },
    "EPL-1.0": {
        "StrongCopyleft": [
            "HansHammel license-compatibility-checker"
        ],
        "WeakCopyleft": [
            "BlueOak License List",
            "librariesio license-compatibility"
        ]
    },
    "OSL-1.1": {
        "StrongCopyleft": [
            "HansHammel license-compatibility-checker"
        ],
        "SaaSCopyleft": [
            "BlueOak License List",
            "librariesio license-compatibility"
        ]
    },
    "APSL-1.2": {
        "WeakCopyleft": [
            "HansHammel license-compatibility-checker"
        ],
        "SaaSCopyleft": [
            "BlueOak License List"
        ]
    }
}