{"__impliedNames":["APAFML","Adobe Postscript AFM License"],"__impliedId":"APAFML","__isFsfFree":true,"__impliedAmbiguousNames":["APAFML"],"facts":{"LicenseName":{"implications":{"__impliedNames":["APAFML"],"__impliedId":"APAFML"},"shortname":"APAFML","otherNames":[]},"SPDX":{"isSPDXLicenseDeprecated":false,"spdxFullName":"Adobe Postscript AFM License","spdxDetailsURL":"http://spdx.org/licenses/APAFML.json","_sourceURL":"https://spdx.org/licenses/APAFML.html","spdxLicIsOSIApproved":false,"spdxSeeAlso":["https://fedoraproject.org/wiki/Licensing/AdobePostscriptAFM"],"_implications":{"__impliedNames":["APAFML","Adobe Postscript AFM License"],"__impliedId":"APAFML","__isOsiApproved":false,"__impliedURLs":[["SPDX","http://spdx.org/licenses/APAFML.json"],[null,"https://fedoraproject.org/wiki/Licensing/AdobePostscriptAFM"]]},"spdxLicenseId":"APAFML"},"Fedora Project Wiki":{"GPLv2 Compat?":"Yes","rating":"Good","Upstream URL":"https://fedoraproject.org/wiki/Licensing/AdobePostscriptAFM","GPLv3 Compat?":"Yes","Short Name":"APAFML","licenseType":"license","_sourceURL":"https://fedoraproject.org/wiki/Licensing:Main?rd=Licensing","Full Name":"Adobe Postscript AFM License","FSF Free?":"Yes","_implications":{"__impliedNames":["Adobe Postscript AFM License"],"__isFsfFree":true,"__impliedAmbiguousNames":["APAFML"],"__impliedJudgement":[["Fedora Project Wiki",{"tag":"PositiveJudgement","contents":"This software Licenses is OK for Fedora"}]]}},"BlueOak License List":{"BlueOakRating":"Silver","url":"https://spdx.org/licenses/APAFML.html","isPermissive":true,"_sourceURL":"https://blueoakcouncil.org/list","name":"Adobe Postscript AFM License","id":"APAFML","_implications":{"__impliedNames":["APAFML","Adobe Postscript AFM License"],"__impliedJudgement":[["BlueOak License List",{"tag":"PositiveJudgement","contents":"Rating is: Silver"}]],"__impliedCopyleft":[["BlueOak License List","NoCopyleft"]],"__calculatedCopyleft":"NoCopyleft","__impliedURLs":[["SPDX","https://spdx.org/licenses/APAFML.html"]]}}},"__impliedJudgement":[["BlueOak License List",{"tag":"PositiveJudgement","contents":"Rating is: Silver"}],["Fedora Project Wiki",{"tag":"PositiveJudgement","contents":"This software Licenses is OK for Fedora"}]],"__impliedCopyleft":[["BlueOak License List","NoCopyleft"]],"__calculatedCopyleft":"NoCopyleft","__isOsiApproved":false,"__impliedURLs":[["SPDX","https://spdx.org/licenses/APAFML.html"],["SPDX","http://spdx.org/licenses/APAFML.json"],[null,"https://fedoraproject.org/wiki/Licensing/AdobePostscriptAFM"]]}