{"__impliedNames":["CC-BY-NC-SA-2.0-FR","Creative Commons Attribution-NonCommercial-ShareAlike 2.0 France"],"__impliedId":"CC-BY-NC-SA-2.0-FR","facts":{"LicenseName":{"implications":{"__impliedNames":["CC-BY-NC-SA-2.0-FR"],"__impliedId":"CC-BY-NC-SA-2.0-FR"},"shortname":"CC-BY-NC-SA-2.0-FR","otherNames":[]},"SPDX":{"isSPDXLicenseDeprecated":false,"spdxFullName":"Creative Commons Attribution-NonCommercial-ShareAlike 2.0 France","spdxDetailsURL":"https://spdx.org/licenses/CC-BY-NC-SA-2.0-FR.json","_sourceURL":"https://spdx.org/licenses/CC-BY-NC-SA-2.0-FR.html","spdxLicIsOSIApproved":false,"spdxSeeAlso":["https://creativecommons.org/licenses/by-nc-sa/2.0/fr/legalcode"],"_implications":{"__impliedNames":["CC-BY-NC-SA-2.0-FR","Creative Commons Attribution-NonCommercial-ShareAlike 2.0 France"],"__impliedId":"CC-BY-NC-SA-2.0-FR","__isOsiApproved":false,"__impliedURLs":[["SPDX","https://spdx.org/licenses/CC-BY-NC-SA-2.0-FR.json"],[null,"https://creativecommons.org/licenses/by-nc-sa/2.0/fr/legalcode"]]},"spdxLicenseId":"CC-BY-NC-SA-2.0-FR"}},"__isOsiApproved":false,"__impliedURLs":[["SPDX","https://spdx.org/licenses/CC-BY-NC-SA-2.0-FR.json"],[null,"https://creativecommons.org/licenses/by-nc-sa/2.0/fr/legalcode"]]}